mwutils/__init__.py
mwutils/cache.py
mwutils/kafka_flask.py
mwutils/kafka_paython_flask.py
mwutils/mw_consul.py
mwutils/mw_redis_util.py
mwutils/mw_time.py
mwutils/sendmail.py
mwutils/update_notify.py
mwutils/utils.py
mwutils-0.1.42.dist-info/LICENSE.txt
mwutils-0.1.42.dist-info/METADATA
mwutils-0.1.42.dist-info/WHEEL
mwutils-0.1.42.dist-info/top_level.txt
mwutils-0.1.42.dist-info/RECORD
