Metadata-Version: 2.2
Name: mwutils
Version: 0.1.42
Summary: cdmaxwin团队常用的utils 
Home-page: https://bitbucket.org/maxwin-inc/mwutils/src
Author: cxhjet
Author-email: cxhjet@qq.com
Classifier: Intended Audience :: Developers
Classifier: License :: OSI Approved :: BSD License
Classifier: Operating System :: OS Independent
Classifier: Programming Language :: Python :: 3.6
License-File: LICENSE.txt
Requires-Dist: redis>=2.10.6
Requires-Dist: python-consul>=1.1.0
Requires-Dist: python-dateutil>=2.7.3
Dynamic: author
Dynamic: author-email
Dynamic: classifier
Dynamic: description
Dynamic: home-page
Dynamic: requires-dist
Dynamic: summary
